Metadata-Version: 1.1
Name: robloxlib
Version: 7.0.0
Summary: A simple library for getting info from ROBLOX's APIs.
Home-page: https://github.com/NoahCristino/robloxlib
Author: Noah Cristino
Author-email: noahcristino@gmail.com
License: MIT
Download-URL: https://github.com/NoahCristino/robloxlib/archive/7.0.tar.gz
Keywords: roblox robloxapi requests
Platform: UNKNOWN
Classifier: Development Status :: 3 - Alpha
Classifier: Topic :: Utilities
Classifier: Programming Language :: Python :: 2 :: Only
Classifier: Topic :: Software Development :: Libraries :: Python Modules
Classifier: License :: OSI Approved :: MIT License
